asyncoff/__init__.py
asyncoff2-0.0.1.dist-info/METADATA
asyncoff2-0.0.1.dist-info/WHEEL
asyncoff2-0.0.1.dist-info/top_level.txt
asyncoff2-0.0.1.dist-info/RECORD
