Metadata-Version: 2.1
Name: asyncoff2
Version: 0.0.1
Summary: Run async functions in synchronous mode
Author: maryimana
Author-email: tombutoyi@gmail.com
Keywords: python,async,asyncoff,sync,async to sync
Classifier: Development Status :: 1 - Planning
Classifier: Intended Audience :: Developers
Classifier: Programming Language :: Python :: 3
Classifier: Operating System :: Unix
Classifier: Operating System :: MacOS :: MacOS X
Classifier: Operating System :: Microsoft :: Windows
